StrictTypePython/__init__.py
StrictTypePython/types.py
tests/test_tests.py
stricttypepython-0.1.0.dist-info/METADATA
stricttypepython-0.1.0.dist-info/WHEEL
stricttypepython-0.1.0.dist-info/top_level.txt
stricttypepython-0.1.0.dist-info/RECORD
